LICENSE
MANIFEST.in
README.md
pyproject.toml
python-ligo-lw.spec
python-ligo-lw.spec.in
setup.py
bin/ligolw_add
bin/ligolw_cut
bin/ligolw_no_ilwdchar
bin/ligolw_print
bin/ligolw_run_sqlite
bin/ligolw_segments
bin/ligolw_sqlite
db2/calib_info.sql
db2/change_creator_db.pl
db2/coinc_sngl.sql
db2/create_base
db2/createall
db2/creator_db_table.txt
db2/dbmdctest.sql
db2/delall.sql
db2/deltest1.sql
db2/deltest2.sql
db2/dropall.sql
db2/external_trigger.sql
db2/exttrig_search.sql
db2/filter.sql
db2/filter_params.sql
db2/frameset.sql
db2/frameset_chanlist.sql
db2/frameset_loc.sql
db2/frameset_writer.sql
db2/gds_trigger.sql
db2/grant.sql
db2/grant_base.sql
db2/gridcert.sql
db2/ilwdtypes.sql
db2/lfn.sql
db2/ligolw_mon.sql
db2/multi_burst.sql
db2/multi_inspiral.sql
db2/process.sql
db2/process_params.sql
db2/runlist.sql
db2/runstats.sql
db2/search_summary.sql
db2/search_summvars.sql
db2/segment.sql
db2/segment_def_map.sql
db2/segment_definer.sql
db2/segment_lfn_map.sql
db2/selectall.sql
db2/seltest1.sql
db2/seltest2.sql
db2/sim_inst.sql
db2/sim_inst_params.sql
db2/sim_type.sql
db2/sim_type_params.sql
db2/sngl_block.sql
db2/sngl_burst.sql
db2/sngl_datasource.sql
db2/sngl_dperiodic.sql
db2/sngl_inspiral.sql
db2/sngl_mime.sql
db2/sngl_ringdown.sql
db2/sngl_transdata.sql
db2/sngl_unmodeled.sql
db2/sngl_unmodeled_v.sql
db2/state_segment.sql
db2/summ_comment.sql
db2/summ_csd.sql
db2/summ_mime.sql
db2/summ_spectrum.sql
db2/summ_statistics.sql
db2/summ_value.sql
db2/tabsmon.sql
db2/waveburst.sql
db2/waveburst_mime.sql
debian/changelog
debian/compat
debian/control
debian/copyright
debian/python3-ligo-lw-bin.install
debian/python3-ligo-lw.install
debian/rules
debian/source/format
etc/ligolw.js
etc/ligolw.xsl
etc/ligolw_dtd.txt
ligo/lw/__init__.py
ligo/lw/tokenizer.cpython-312-x86_64-linux-gnu.so
ligo/lw/__pycache__/__init__.cpython-312.pyc
ligo/lw/__pycache__/ligolw.cpython-312.pyc
ligo/lw/__pycache__/lsctables.cpython-312.pyc
ligo/lw/__pycache__/types.cpython-312.pyc
python_ligo_lw.egg-info/PKG-INFO
python_ligo_lw.egg-info/SOURCES.txt
python_ligo_lw.egg-info/dependency_links.txt
python_ligo_lw.egg-info/top_level.txt
