Metadata-Version: 2.4
Name: python-ligo-lw
Version: 2.1.0
Summary: Python LIGO Light-Weight XML I/O Library
Home-page: https://git.ligo.org/kipp.cannon/python-ligo-lw
Author: Kipp Cannon
Author-email: Kipp Cannon <kipp@g.ecc.u-tokyo.ac.jp>
License:                     GNU GENERAL PUBLIC LICENSE
Project-URL: Homepage, https://git.ligo.org/kipp/python-ligo-lw
Classifier: Development Status :: 6 - Mature
Classifier: Intended Audience :: Science/Research
Classifier: License :: OSI Approved :: GNU General Public License v2 or later (GPLv2+)
Classifier: Natural Language :: English
Classifier: Operating System :: POSIX
Classifier: Programming Language :: Python :: 3
Classifier: Topic :: Scientific/Engineering :: Astronomy
Classifier: Topic :: Scientific/Engineering :: Physics
Classifier: Topic :: Software Development :: Libraries
Classifier: Topic :: Text Processing :: Markup :: XML
License-File: LICENSE
Dynamic: author
Dynamic: home-page
Dynamic: license-file
